{
  "annotations": {
    "list": [
      {
        "builtIn": 1,
        "datasource": {
          "type": "grafana",
          "uid": "-- Grafana --"
        },
        "enable": true,
        "hide": true,
        "iconColor": "rgba(0, 211, 255, 1)",
        "name": "Annotations & Alerts",
        "type": "dashboard"
      }
    ]
  },
  "editable": true,
  "fiscalYearStartMonth": 0,
  "graphTooltip": 0,
  "id": 0,
  "links": [],
  "panels": [
    {
      "collapsed": false,
      "gridPos": {
        "h": 1,
        "w": 24,
        "x": 0,
        "y": 0
      },
      "id": 7,
      "panels": [],
      "title": "PostgreSQL Health & Performance",
      "type": "row"
    },
    {
      "datasource": {
        "type": "prometheus",
        "uid": "P4169E866C3094E38"
      },
      "fieldConfig": {
        "defaults": {
          "color": {
            "mode": "continuous-GrYlRd"
          },
          "mappings": [],
          "thresholds": {
            "mode": "absolute",
            "steps": [
              {
                "color": "green",
                "value": 0
              },
              {
                "color": "red",
                "value": 80
              }
            ]
          }
        },
        "overrides": []
      },
      "gridPos": {
        "h": 8,
        "w": 6,
        "x": 0,
        "y": 1
      },
      "id": 8,
      "options": {
        "displayMode": "lcd",
        "legend": {
          "calcs": [],
          "displayMode": "list",
          "placement": "bottom",
          "showLegend": false
        },
        "maxVizHeight": 300,
        "minVizHeight": 16,
        "minVizWidth": 8,
        "namePlacement": "auto",
        "orientation": "horizontal",
        "reduceOptions": {
          "calcs": [
            "lastNotNull"
          ],
          "fields": "",
          "values": false
        },
        "showUnfilled": true,
        "sizing": "auto",
        "valueMode": "color"
      },
      "pluginVersion": "12.3.3",
      "targets": [
        {
          "editorMode": "code",
          "expr": "max(cnpg_collector_up{namespace=\"$Namespace\", cluster=\"$Cluster\"})",
          "legendFormat": "__auto",
          "range": true,
          "refId": "A"
        }
      ],
      "title": "Cluster Status",
      "type": "bargauge"
    },
    {
      "datasource": {
        "type": "prometheus",
        "uid": "P4169E866C3094E38"
      },
      "fieldConfig": {
        "defaults": {
          "color": {
            "mode": "continuous-GrYlRd"
          },
          "mappings": [],
          "thresholds": {
            "mode": "absolute",
            "steps": [
              {
                "color": "green",
                "value": 0
              },
              {
                "color": "red",
                "value": 80
              }
            ]
          }
        },
        "overrides": []
      },
      "gridPos": {
        "h": 8,
        "w": 6,
        "x": 6,
        "y": 1
      },
      "id": 9,
      "options": {
        "displayMode": "lcd",
        "legend": {
          "calcs": [],
          "displayMode": "list",
          "placement": "bottom",
          "showLegend": false
        },
        "maxVizHeight": 300,
        "minVizHeight": 16,
        "minVizWidth": 8,
        "namePlacement": "auto",
        "orientation": "horizontal",
        "reduceOptions": {
          "calcs": [
            "lastNotNull"
          ],
          "fields": "",
          "values": false
        },
        "showUnfilled": true,
        "sizing": "auto",
        "valueMode": "color"
      },
      "pluginVersion": "12.3.3",
      "targets": [
        {
          "editorMode": "code",
          "expr": "sum(cnpg_backends_total{namespace=\"$Namespace\", pod=~\"^$Cluster-.*\"}) by (usename)",
          "legendFormat": "__auto",
          "range": true,
          "refId": "A"
        }
      ],
      "title": "Active Connections",
      "type": "bargauge"
    },
    {
      "datasource": {
        "type": "prometheus",
        "uid": "P4169E866C3094E38"
      },
      "fieldConfig": {
        "defaults": {
          "color": {
            "mode": "palette-classic"
          },
          "custom": {
            "axisBorderShow": false,
            "axisCenteredZero": false,
            "axisColorMode": "text",
            "axisLabel": "",
            "axisPlacement": "auto",
            "barAlignment": 0,
            "barWidthFactor": 0.6,
            "drawStyle": "line",
            "fillOpacity": 0,
            "gradientMode": "none",
            "hideFrom": {
              "legend": false,
              "tooltip": false,
              "viz": false
            },
            "insertNulls": false,
            "lineInterpolation": "linear",
            "lineWidth": 1,
            "pointSize": 5,
            "scaleDistribution": {
              "type": "linear"
            },
            "showPoints": "auto",
            "showValues": false,
            "spanNulls": false,
            "stacking": {
              "group": "A",
              "mode": "none"
            },
            "thresholdsStyle": {
              "mode": "off"
            }
          },
          "mappings": [],
          "thresholds": {
            "mode": "absolute",
            "steps": [
              {
                "color": "green",
                "value": 0
              },
              {
                "color": "red",
                "value": 80
              }
            ]
          }
        },
        "overrides": []
      },
      "gridPos": {
        "h": 8,
        "w": 6,
        "x": 12,
        "y": 1
      },
      "id": 6,
      "options": {
        "legend": {
          "calcs": [],
          "displayMode": "hidden",
          "placement": "right",
          "showLegend": false
        },
        "tooltip": {
          "hideZeros": false,
          "mode": "single",
          "sort": "none"
        }
      },
      "pluginVersion": "12.3.3",
      "targets": [
        {
          "editorMode": "code",
          "expr": "cnpg_pg_replication_lag{namespace=\"$Namespace\", pod=~\"^$Cluster-.*\"}",
          "legendFormat": "__auto",
          "range": true,
          "refId": "A"
        }
      ],
      "title": "Replication Lag",
      "type": "timeseries"
    },
    {
      "datasource": {
        "type": "prometheus",
        "uid": "P4169E866C3094E38"
      },
      "description": "At its core, Cache Hit Ratio is the ultimate measure of how efficiently your database is using its memory (RAM)",
      "fieldConfig": {
        "defaults": {
          "color": {
            "mode": "palette-classic"
          },
          "custom": {
            "axisBorderShow": false,
            "axisCenteredZero": false,
            "axisColorMode": "text",
            "axisLabel": "",
            "axisPlacement": "auto",
            "barAlignment": 0,
            "barWidthFactor": 0.6,
            "drawStyle": "line",
            "fillOpacity": 25,
            "gradientMode": "none",
            "hideFrom": {
              "legend": false,
              "tooltip": false,
              "viz": false
            },
            "insertNulls": false,
            "lineInterpolation": "linear",
            "lineWidth": 1,
            "pointSize": 5,
            "scaleDistribution": {
              "type": "linear"
            },
            "showPoints": "auto",
            "showValues": false,
            "spanNulls": false,
            "stacking": {
              "group": "A",
              "mode": "none"
            },
            "thresholdsStyle": {
              "mode": "off"
            }
          },
          "mappings": [],
          "thresholds": {
            "mode": "absolute",
            "steps": [
              {
                "color": "green",
                "value": 0
              },
              {
                "color": "red",
                "value": 80
              }
            ]
          }
        },
        "overrides": []
      },
      "gridPos": {
        "h": 8,
        "w": 6,
        "x": 18,
        "y": 1
      },
      "id": 3,
      "options": {
        "legend": {
          "calcs": [],
          "displayMode": "hidden",
          "placement": "right",
          "showLegend": false
        },
        "tooltip": {
          "hideZeros": false,
          "mode": "single",
          "sort": "none"
        }
      },
      "pluginVersion": "12.3.3",
      "targets": [
        {
          "editorMode": "code",
          "expr": "sum(rate(cnpg_pg_stat_database_blks_hit_total{namespace=\"$Namespace\"}[10m]))\n/\n(sum(rate(cnpg_pg_stat_database_blks_hit_total{namespace=\"$Namespace\"}[10m])) + sum(rate(cnpg_pg_stat_database_blks_read_total{namespace=\"$Namespace\"}[10m])))",
          "legendFormat": "__auto",
          "range": true,
          "refId": "A"
        }
      ],
      "title": "Cache Hit Ratio",
      "type": "timeseries"
    },
    {
      "datasource": {
        "type": "prometheus",
        "uid": "P4169E866C3094E38"
      },
      "description": "Transaction Commit Rate is the most direct measurement of how much actual work your database is accomplishing at any given moment.",
      "fieldConfig": {
        "defaults": {
          "color": {
            "mode": "continuous-GrYlRd"
          },
          "mappings": [],
          "thresholds": {
            "mode": "absolute",
            "steps": [
              {
                "color": "green",
                "value": 0
              },
              {
                "color": "red",
                "value": 80
              }
            ]
          }
        },
        "overrides": []
      },
      "gridPos": {
        "h": 8,
        "w": 12,
        "x": 0,
        "y": 9
      },
      "id": 4,
      "options": {
        "displayMode": "lcd",
        "legend": {
          "calcs": [],
          "displayMode": "list",
          "placement": "bottom",
          "showLegend": false
        },
        "maxVizHeight": 300,
        "minVizHeight": 16,
        "minVizWidth": 8,
        "namePlacement": "auto",
        "orientation": "horizontal",
        "reduceOptions": {
          "calcs": [
            "lastNotNull"
          ],
          "fields": "",
          "values": false
        },
        "showUnfilled": true,
        "sizing": "auto",
        "valueMode": "color"
      },
      "pluginVersion": "12.3.3",
      "targets": [
        {
          "editorMode": "code",
          "expr": "sum(rate(cnpg_pg_stat_database_xact_commit_total{namespace=\"$Namespace\"}[5m])) by (datname)",
          "legendFormat": "__auto",
          "range": true,
          "refId": "A"
        }
      ],
      "title": "Transaction Commit Rate",
      "type": "bargauge"
    },
    {
      "datasource": {
        "type": "prometheus",
        "uid": "P4169E866C3094E38"
      },
      "fieldConfig": {
        "defaults": {
          "fieldMinMax": false,
          "mappings": [],
          "thresholds": {
            "mode": "absolute",
            "steps": [
              {
                "color": "green",
                "value": 0
              }
            ]
          },
          "unit": "short"
        },
        "overrides": []
      },
      "gridPos": {
        "h": 8,
        "w": 12,
        "x": 12,
        "y": 9
      },
      "id": 5,
      "options": {
        "colorMode": "background",
        "graphMode": "none",
        "justifyMode": "auto",
        "orientation": "auto",
        "percentChangeColorMode": "standard",
        "reduceOptions": {
          "calcs": [
            "lastNotNull"
          ],
          "fields": "",
          "values": false
        },
        "showPercentChange": false,
        "textMode": "auto",
        "wideLayout": true
      },
      "pluginVersion": "12.3.3",
      "targets": [
        {
          "editorMode": "code",
          "expr": "sum(cnpg_pg_database_size_bytes{namespace=\"$Namespace\"}) by (datname)",
          "legendFormat": "__auto",
          "range": true,
          "refId": "A"
        }
      ],
      "title": "Database Sizes",
      "type": "stat"
    },
    {
      "collapsed": false,
      "gridPos": {
        "h": 1,
        "w": 24,
        "x": 0,
        "y": 17
      },
      "id": 10,
      "panels": [],
      "title": "Backup & WAL Archiving",
      "type": "row"
    },
    {
      "datasource": {
        "type": "prometheus",
        "uid": "P4169E866C3094E38"
      },
      "fieldConfig": {
        "defaults": {
          "mappings": [],
          "thresholds": {
            "mode": "absolute",
            "steps": [
              {
                "color": "green",
                "value": 0
              },
              {
                "color": "red",
                "value": 80
              }
            ]
          },
          "unit": "short"
        },
        "overrides": []
      },
      "gridPos": {
        "h": 8,
        "w": 5,
        "x": 0,
        "y": 18
      },
      "id": 11,
      "options": {
        "colorMode": "background",
        "graphMode": "none",
        "justifyMode": "auto",
        "orientation": "auto",
        "percentChangeColorMode": "standard",
        "reduceOptions": {
          "calcs": [
            "lastNotNull"
          ],
          "fields": "",
          "values": false
        },
        "showPercentChange": false,
        "textMode": "auto",
        "wideLayout": true
      },
      "pluginVersion": "12.3.3",
      "targets": [
        {
          "editorMode": "code",
          "expr": "sum(cnpg_pg_stat_archiver_archived_count_total{namespace=\"$Namespace\", pod=~\"^$Cluster-.*\"}[5m])",
          "legendFormat": "__auto",
          "range": true,
          "refId": "A"
        }
      ],
      "title": "WAL Archiving Rate Success",
      "type": "stat"
    },
    {
      "datasource": {
        "type": "prometheus",
        "uid": "P4169E866C3094E38"
      },
      "fieldConfig": {
        "defaults": {
          "mappings": [],
          "thresholds": {
            "mode": "absolute",
            "steps": [
              {
                "color": "green",
                "value": 0
              },
              {
                "color": "red",
                "value": 0
              }
            ]
          },
          "unit": "short"
        },
        "overrides": []
      },
      "gridPos": {
        "h": 8,
        "w": 5,
        "x": 5,
        "y": 18
      },
      "id": 12,
      "options": {
        "colorMode": "background",
        "graphMode": "none",
        "justifyMode": "auto",
        "orientation": "auto",
        "percentChangeColorMode": "standard",
        "reduceOptions": {
          "calcs": [
            "lastNotNull"
          ],
          "fields": "",
          "values": false
        },
        "showPercentChange": false,
        "textMode": "auto",
        "wideLayout": true
      },
      "pluginVersion": "12.3.3",
      "targets": [
        {
          "editorMode": "code",
          "expr": "sum(cnpg_pg_stat_archiver_failed_count_total{namespace=\"$Namespace\", pod=~\"^$Cluster-.*\"}[5m])",
          "legendFormat": "__auto",
          "range": true,
          "refId": "A"
        }
      ],
      "title": "WAL Archiving Rate Failure",
      "type": "stat"
    },
    {
      "datasource": {
        "type": "prometheus",
        "uid": "P4169E866C3094E38"
      },
      "fieldConfig": {
        "defaults": {
          "mappings": [],
          "thresholds": {
            "mode": "absolute",
            "steps": [
              {
                "color": "green",
                "value": 0
              }
            ]
          },
          "unit": "short"
        },
        "overrides": []
      },
      "gridPos": {
        "h": 8,
        "w": 14,
        "x": 10,
        "y": 18
      },
      "id": 13,
      "options": {
        "colorMode": "value",
        "graphMode": "area",
        "justifyMode": "auto",
        "orientation": "auto",
        "percentChangeColorMode": "standard",
        "reduceOptions": {
          "calcs": [
            "lastNotNull"
          ],
          "fields": "",
          "values": false
        },
        "showPercentChange": false,
        "textMode": "auto",
        "wideLayout": true
      },
      "pluginVersion": "12.3.3",
      "targets": [
        {
          "editorMode": "code",
          "expr": "cnpg_collector_wal_bytes{namespace=\"$Namespace\", pod=\"$Cluster-1\"}",
          "legendFormat": "__auto",
          "range": true,
          "refId": "A"
        }
      ],
      "title": "WAL Size on Disk",
      "type": "stat"
    },
    {
      "collapsed": false,
      "gridPos": {
        "h": 1,
        "w": 24,
        "x": 0,
        "y": 26
      },
      "id": 14,
      "panels": [],
      "title": "Hardware & Infrastructure",
      "type": "row"
    },
    {
      "datasource": {
        "type": "prometheus",
        "uid": "P4169E866C3094E38"
      },
      "fieldConfig": {
        "defaults": {
          "mappings": [],
          "thresholds": {
            "mode": "percentage",
            "steps": [
              {
                "color": "green",
                "value": 0
              },
              {
                "color": "orange",
                "value": 70
              },
              {
                "color": "red",
                "value": 85
              }
            ]
          },
          "unit": "percentunit"
        },
        "overrides": []
      },
      "gridPos": {
        "h": 13,
        "w": 6,
        "x": 0,
        "y": 27
      },
      "id": 15,
      "options": {
        "minVizHeight": 75,
        "minVizWidth": 75,
        "orientation": "auto",
        "reduceOptions": {
          "calcs": [
            "lastNotNull"
          ],
          "fields": "",
          "values": false
        },
        "showThresholdLabels": false,
        "showThresholdMarkers": false,
        "sizing": "auto"
      },
      "pluginVersion": "12.3.3",
      "targets": [
        {
          "editorMode": "code",
          "expr": "sum by (pod) (\n  label_replace(\n    rate(container_cpu_usage{job=~\"^$Namespace/$Cluster-.*\"}[5m]), \n    \"pod\", \n    \"$1\", \n    \"job\", \n    \".*/(.*)\"\n  )\n) / max(kube_pod_container_resource_limits{namespace=\"$Namespace\", pod=~\"^$Cluster-.*\", resource=\"cpu\"}) by (pod)",
          "hide": false,
          "legendFormat": "__auto",
          "range": true,
          "refId": "A"
        },
        {
          "datasource": {
            "type": "prometheus",
            "uid": "P4169E866C3094E38"
          },
          "editorMode": "code",
          "expr": "",
          "hide": false,
          "instant": false,
          "legendFormat": "__auto",
          "range": true,
          "refId": "B"
        }
      ],
      "title": "CPU Usage %",
      "type": "gauge"
    },
    {
      "datasource": {
        "type": "prometheus",
        "uid": "P4169E866C3094E38"
      },
      "fieldConfig": {
        "defaults": {
          "mappings": [],
          "thresholds": {
            "mode": "percentage",
            "steps": [
              {
                "color": "green",
                "value": 0
              },
              {
                "color": "orange",
                "value": 70
              },
              {
                "color": "red",
                "value": 85
              }
            ]
          },
          "unit": "percentunit"
        },
        "overrides": []
      },
      "gridPos": {
        "h": 13,
        "w": 6,
        "x": 6,
        "y": 27
      },
      "id": 16,
      "options": {
        "minVizHeight": 75,
        "minVizWidth": 75,
        "orientation": "auto",
        "reduceOptions": {
          "calcs": [
            "lastNotNull"
          ],
          "fields": "",
          "values": false
        },
        "showThresholdLabels": false,
        "showThresholdMarkers": false,
        "sizing": "auto"
      },
      "pluginVersion": "12.3.3",
      "targets": [
        {
          "editorMode": "code",
          "expr": "sum by (pod) (\n  label_replace(\n    container_memory_usage_bytes{job=~\"^$Namespace/$Cluster-.*\"}, \n    \"pod\", \n    \"$1\", \n    \"job\", \n    \".*/(.*)\"\n  )\n) \n/ \nmax by (pod) (\n  kube_pod_container_resource_limits{namespace=\"$Namespace\", pod=~\"^$Cluster-.*\", resource=\"memory\"}\n)",
          "hide": false,
          "legendFormat": "__auto",
          "range": true,
          "refId": "A"
        }
      ],
      "title": "Memory Usage %",
      "type": "gauge"
    },
    {
      "datasource": {
        "type": "prometheus",
        "uid": "P4169E866C3094E38"
      },
      "fieldConfig": {
        "defaults": {
          "mappings": [],
          "thresholds": {
            "mode": "percentage",
            "steps": [
              {
                "color": "green",
                "value": 0
              },
              {
                "color": "orange",
                "value": 70
              },
              {
                "color": "red",
                "value": 85
              }
            ]
          },
          "unit": "none"
        },
        "overrides": []
      },
      "gridPos": {
        "h": 13,
        "w": 6,
        "x": 12,
        "y": 27
      },
      "id": 17,
      "options": {
        "minVizHeight": 75,
        "minVizWidth": 75,
        "orientation": "auto",
        "reduceOptions": {
          "calcs": [
            "lastNotNull"
          ],
          "fields": "",
          "values": false
        },
        "showThresholdLabels": false,
        "showThresholdMarkers": false,
        "sizing": "auto"
      },
      "pluginVersion": "12.3.3",
      "targets": [
        {
          "editorMode": "code",
          "expr": "max by (pod) (\n  kube_pod_container_status_restarts_total{namespace=\"$Namespace\", pod=~\"^$Cluster-.*\"}\n)",
          "hide": false,
          "legendFormat": "__auto",
          "range": true,
          "refId": "A"
        }
      ],
      "title": "Pod Restarts",
      "type": "gauge"
    },
    {
      "collapsed": false,
      "gridPos": {
        "h": 1,
        "w": 24,
        "x": 0,
        "y": 40
      },
      "id": 18,
      "panels": [],
      "title": "Logs",
      "type": "row"
    },
    {
      "datasource": {
        "type": "victoriametrics-logs-datasource",
        "uid": "PD775F2863313E6C7"
      },
      "fieldConfig": {
        "defaults": {},
        "overrides": []
      },
      "gridPos": {
        "h": 16,
        "w": 24,
        "x": 0,
        "y": 41
      },
      "id": 19,
      "options": {
        "dedupStrategy": "none",
        "detailsMode": "sidebar",
        "enableInfiniteScrolling": false,
        "enableLogDetails": true,
        "showControls": true,
        "showLabels": false,
        "showTime": false,
        "sortOrder": "Descending",
        "syntaxHighlighting": true,
        "timestampResolution": "ns",
        "wrapLogMessage": true
      },
      "pluginVersion": "12.3.3",
      "targets": [
        {
          "datasource": {
            "type": "victoriametrics-logs-datasource",
            "uid": "PD775F2863313E6C7"
          },
          "direction": "desc",
          "editorMode": "code",
          "expr": "cnpg.io/cluster: \"$Cluster\" AND k8s.namespace.name: \"$Namespace\"",
          "queryType": "instant",
          "refId": "A"
        }
      ],
      "title": "Logging",
      "type": "logs"
    }
  ],
  "preload": false,
  "refresh": "5s",
  "schemaVersion": 42,
  "tags": [],
  "templating": {
    "list": [
      {
        "current": {
          "text": "postgres",
          "value": "postgres"
        },
        "definition": "label_values(cnpg_collector_up,namespace)",
        "description": "Name of the namespace where the CNPG cluster lives in",
        "name": "Namespace",
        "options": [],
        "query": {
          "qryType": 1,
          "query": "label_values(cnpg_collector_up,namespace)",
          "refId": "PrometheusVariableQueryEditor-VariableQuery"
        },
        "refresh": 1,
        "regex": "",
        "type": "query"
      },
      {
        "current": {
          "text": "postgresql-cluster",
          "value": "postgresql-cluster"
        },
        "definition": "label_values(cnpg_collector_up,cluster)",
        "description": "Name of the CNPG Cluster to pull in data from",
        "name": "Cluster",
        "options": [],
        "query": {
          "qryType": 1,
          "query": "label_values(cnpg_collector_up,cluster)",
          "refId": "PrometheusVariableQueryEditor-VariableQuery"
        },
        "refresh": 1,
        "regex": "",
        "type": "query"
      }
    ]
  },
  "time": {
    "from": "now-1h",
    "to": "now"
  },
  "timepicker": {},
  "timezone": "browser",
  "title": "Cloudnative PostgreSQL Database Monitoring",
  "uid": "obbmrs2",
  "version": 3
}